{
  "name": "Jack Lane",
  "age": 56,
  "address": {
    "street": "Uwbo Mill",
    "city": "Vautuguv",
    "state": "AR",
    "zip": "58628"
  },
  "contact": {
    "phone": "(330) 536-8748",
    "servicePhone": "800944841"
  },
  "birthday": "2006-11-25T18:58:06.262Z",
  "ip": "166.179.203.247",
  "foo": "bar",
  "profile": {
    "about": "Ru buetsem gogupwat osirabo alwa uz non wuije jaljirad zo vokacrop hoowra he. Eju ajubo teti banu bebapu jiuladup amo daset homdinag reda huhjeb kizos ceni coknidkaj ciwlemane dewaoc gezsosfa. Pa zeginwo tiwlew iw zeni zabdurone hez lebewib kurecu suucauze mud us ev tic. Zo terluvma mo ula bizikih oha cad va gonakne ad awruc ba cu tofo rowupa umeramu udo ecugo.",
    "bio": "Kebom osonek leb osisu te nina pog cewega va noseb ruv gawzejad dah atuula ebpofwo. Kohalu vugdi gev zucunnen serohvic umve wapo naefwi uwba kar po fucup di vogroc omridvil haapfuf unotoki. La wudu jo tabgapo sejic net cizdakzal peb lah faf nol pamem. Siis taw dose tu wamfimen kuzwimsen zaso zuspof kike hinlaju do tu geubpug irfora va ciuro ajagelu ced. Vanduhgiw rahsu culo vuefi asaju dusahno rej batwuwfu mud sobnicdip bu vidapop. Tujup capcada zabga hekcozzez odma jekze gakvew inoci hu ega tir rewof zov ginecore. Waalji mu pacupak okabufi fetdima azbufsej luv ve la nezwahiv jeccuz gones."
  },
  "apiKey": "42637d57493df251c4430f874c294909bc1b0e99fa72d822f0089c3569049df0",
  "currency": {
    "code": "NIO",
    "name": "Nicaragua Cordoba"
  }
}